ai_six/__init__.py
ai_six/.claude/settings.local.json
ai_six/a2a_client/__init__.py
ai_six/a2a_client/a2a_client.py
ai_six/a2a_client/a2a_executor.py
ai_six/a2a_client/a2a_manager.py
ai_six/a2a_client/a2a_message_pump.py
ai_six/agent/README.md
ai_six/agent/__init__.py
ai_six/agent/agent.py
ai_six/agent/config.py
ai_six/agent/session.py
ai_six/agent/session_manager.py
ai_six/agent/summarizer.py
ai_six/agent/tool_manager.py
ai_six/llm_providers/__init__.py
ai_six/llm_providers/model_info.py
ai_six/llm_providers/ollama_provider.py
ai_six/llm_providers/openai_provider.py
ai_six/mcp_client/mcp_client.py
ai_six/mcp_tools/fs_mcp_server.py
ai_six/mcp_tools/github_mcp_server.sh
ai_six/object_model/__init__.py
ai_six/object_model/agent_tool.py
ai_six/object_model/llm_provider.py
ai_six/object_model/message.py
ai_six/object_model/tool.py
ai_six/tests/__init__.py
ai_six/tests/memory/__init__.py
ai_six/tests/memory/mock_agent.py
ai_six/tests/memory/test_agent_memory.py
ai_six/tests/memory/test_agent_summarization.py
ai_six/tests/memory/test_memory_tools.py
ai_six/tests/memory/test_session.py
ai_six/tests/memory/test_session_manager.py
ai_six/tests/memory/test_setup.py
ai_six/tests/memory/test_summarization_integration.py
ai_six/tests/memory/test_summarizer.py
ai_six/tests/providers/__init__.py
ai_six/tests/providers/test_ollama_provider.py
ai_six/tests/providers/test_openai_provider.py
ai_six/tests/providers/test_openai_streaming.py
ai_six/tests/tools/__init__.py
ai_six/tests/tools/test_discover_mcp_tools.py
ai_six/tests/tools/test_mcp_tools.py
ai_six/tests/tools/test_tool_filtering.py
ai_six/tests/tools/test_web_fetch.py
ai_six/tests/tools/test_web_fetch_integration.py
ai_six/tests/tools/bootstrap/__init__.py
ai_six/tests/tools/bootstrap/test_bootstrap.py
ai_six/tests/tools/claude/__init__.py
ai_six/tests/tools/claude/test_claude.py
ai_six/tests/tools/file_system/__init__.py
ai_six/tests/tools/file_system/test_awk.py
ai_six/tests/tools/file_system/test_cat.py
ai_six-0.14.6.dist-info/METADATA
ai_six-0.14.6.dist-info/WHEEL
ai_six-0.14.6.dist-info/RECORD
