Metadata-Version: 2.4
Name: ai-six
Version: 0.14.6
Summary: Agentic AI focused on ubiquitous tool using
Project-URL: Homepage, https://deepwiki.com/Sayfan-AI/ai-six
Project-URL: Repository, https://github.com/the-gigi/ai-six
Project-URL: Issues, https://github.com/the-gigi/ai-six/issues
Author: Gigi Sayfan
License: MIT
Classifier: Development Status :: 4 - Beta
Classifier: Intended Audience :: Developers
Classifier: License :: OSI Approved :: MIT License
Classifier: Operating System :: OS Independent
Classifier: Programming Language :: Python :: 3
Classifier: Programming Language :: Python :: 3.10
Classifier: Programming Language :: Python :: 3.11
Classifier: Programming Language :: Python :: 3.12
Classifier: Topic :: Scientific/Engineering :: Artificial Intelligence
Classifier: Topic :: Software Development :: Libraries :: Python Modules
Requires-Python: >=3.10
Requires-Dist: a2a-sdk[http-server]
Requires-Dist: anthropic
Requires-Dist: chainlit
Requires-Dist: kubernetes
Requires-Dist: mcp>=1.14.1
Requires-Dist: ollama
Requires-Dist: openai
Requires-Dist: pathology
Requires-Dist: python-dotenv
Requires-Dist: pyyaml
Requires-Dist: requests
Requires-Dist: sh
Requires-Dist: slack-bolt
Requires-Dist: toml
Provides-Extra: dev
Requires-Dist: debugpy; extra == 'dev'
Requires-Dist: pytest; extra == 'dev'
Requires-Dist: pytest-cov; extra == 'dev'
